[
  {
    "id": 1,
    "user_id": 6,
    "related_user_id": [4],
    "workspace_id": 7,
    "title": "Play Soccer",
    "location": "Stadium",
    "description": "Mô tả hoặc phân công chi tiết sẽ ở đây",
    "workStatus": "Completed",
    "done": 2,
    "close": true,
    "date": {
      "start": 17000,
      "end": 21000,
      "day": 6,
      "month": 7,
      "year": 2023
    }
  },
  {
    "id": 2,
    "user_id": 6,
    "related_user_id": [3, 4],
    "workspace_id": 8,
    "title": "Game",
    "location": "X-Game Tran Dai Nghia",
    "description": "Mô tả hoặc phân công chi tiết sẽ ở đây",
    "done": 3,
    "close": true,
    "workStatus": "Completed",
    "date": {
      "start": 18000,
      "end": 23000,
      "day": 3,
      "month": 7,
      "year": 2023
    }
  },
  {
    "id": 3,
    "user_id": 6,
    "related_user_id": [1, 4],
    "workspace_id": 8,
    "title": "Drink Coffee",
    "location": "The Coffee House",
    "description": "Mô tả hoặc phân công chi tiết sẽ ở đây",
    "done": 3,
    "close": true,
    "workStatus": "Completed",
    "date": {
      "start": 23000,
      "end": 40000,
      "day": 3,
      "month": 7,
      "year": 2023
    }
  },
  {
    "id": 4,
    "user_id": 6,
    "related_user_id": [1, 5],
    "workspace_id": 7,
    "title": "Jogging",
    "location": "Thong Nhat Park",
    "description": "Mô tả hoặc phân công chi tiết sẽ ở đây",
    "done": 3,
    "close": true,
    "workStatus": "Completed",
    "date": {
      "start": 42000,
      "end": 50000,
      "day": 3,
      "month": 7,
      "year": 2023
    }
  },
  {
    "id": 5,
    "user_id": 6,
    "related_user_id": [2, 5],
    "workspace_id": 9,
    "title": "Learn Japanese",
    "location": "School",
    "description": "Mô tả hoặc phân công chi tiết sẽ ở đây",
    "done": 3,
    "close": true,
    "workStatus": "Completed",
    "date": {
      "start": 27000,
      "end": 29000,
      "day": 6,
      "month": 7,
      "year": 2023
    }
  },
  {
    "id": 6,
    "user_id": 6,
    "related_user_id": [2, 5],
    "workspace_id": 9,
    "title": "Learn EngLish",
    "location": "School",
    "description": "Mô tả hoặc phân công chi tiết sẽ ở đây",
    "done": 3,
    "close": true,
    "workStatus": "Completed",
    "date": {
      "start": 30000,
      "end": 35000,
      "day": 5,
      "month": 7,
      "year": 2023
    }
  },
  {
    "id": 7,
    "user_id": 6,
    "related_user_id": [2, 5],
    "workspace_id": 8,
    "title": "Watch Film",
    "location": "Cinema",
    "description": "Mô tả hoặc phân công chi tiết sẽ ở đây",
    "done": 3,
    "close": true,
    "workStatus": "Completed",
    "date": {
      "start": 36000,
      "end": 40000,
      "day": 5,
      "month": 7,
      "year": 2023
    }
  },
  {
    "id": 8,
    "user_id": 6,
    "related_user_id": [3, 5],
    "workspace_id": 9,
    "title": "Work in Lab",
    "location": "B1-1002",
    "description": "Mô tả hoặc phân công chi tiết sẽ ở đây",
    "done": 3,
    "close": true,
    "workStatus": "Completed",
    "date": {
      "start": 41000,
      "end": 47000,
      "day": 4,
      "month": 7,
      "year": 2023
    }
  },
  {
    "id": 9,
    "user_id": 6,
    "related_user_id": [4, 5],
    "workspace_id": 9,
    "title": "Camping",
    "location": "Yen So Park",
    "description": "Mô tả hoặc phân công chi tiết sẽ ở đây",
    "done": 3,
    "close": true,
    "workStatus": "Completed",
    "date": {
      "start": 50000,
      "end": 60000,
      "day": 4,
      "month": 7,
      "year": 2023
    }
  },
  {
    "id": 10,
    "user_id": 6,
    "related_user_id": [2, 4],
    "workspace_id": 7,
    "title": "Do my homework",
    "location": "Circle K",
    "description": "Mô tả hoặc phân công chi tiết sẽ ở đây",
    "done": 3,
    "close": true,
    "workStatus": "Completed",
    "date": {
      "start": 65000,
      "end": 75000,
      "day": 4,
      "month": 7,
      "year": 2023
    }
  },
  {
    "id": 11,
    "user_id": 6,
    "related_user_id": [],
    "workspace_id": 10,
    "title": "Dạy con học",
    "location": "Home",
    "description": "Mô tả hoặc phân công chi tiết sẽ ở đây",
    "done": 1,
    "close": true,
    "workStatus": "Completed",
    "date": {
      "start": 35000,
      "end": 45000,
      "day": 1,
      "month": 7,
      "year": 2023
    }
  },
  {
    "id": 12,
    "user_id": 6,
    "related_user_id": [],
    "workspace_id": 11,
    "title": "Lên tài liệu",
    "location": "Home",
    "description": "Mô tả hoặc phân công chi tiết sẽ ở đây",
    "done": 1,
    "close": true,
    "workStatus": "Completed",
    "date": {
      "start": 55000,
      "end": 75000,
      "day": 1,
      "month": 7,
      "year": 2023
    }
  }
]
